SamTech_STT/__init__.py
SamTech_STT/index.html
SamTech_STT/input.txt
SamTech_STT/script.js
SamTech_STT/styles.css
SamTech_STT-0.6.dist-info/METADATA
SamTech_STT-0.6.dist-info/WHEEL
SamTech_STT-0.6.dist-info/top_level.txt
SamTech_STT-0.6.dist-info/RECORD
