Metadata-Version: 2.1
Name: SamTech_STT
Version: 0.6
Summary: A simple Speech-To-Text Package developed by Samrat Paul
Home-page: https://github.com/SamratPaul16
Author-email: sam@samtech.gmail.com
Requires-Dist: selenium
Requires-Dist: webdriver-manager
